example/non_stall_pipeline.v
module non_stall_pipeline (
    input           clk,
    input  [WIDTH-1:0] datain,
    output [WIDTH-1:0] dataout
);

parameter WIDTH = 100;

reg [WIDTH-1:0] pipe1_data;
reg [WIDTH-1:0] pipe2_data;
reg [WIDTH-1:0] pipe3_data;

always @(posedge clk) begin
    pipe1_data <= datain;
end

always @(posedge clk) begin
    pipe2_data <= pipe1_data;
end

always @(posedge clk) begin
    pipe3_data <= pipe2_data;
end

assign dataout = pipe3_data;

endmodule

example/tb_non_stall_pipeline.v
`timescale 1ns / 1ps

module tb_non_stall_pipeline;

    // 参数定义
    parameter WIDTH = 100;

    // 信号声明
    reg         clk;
    reg  [WIDTH-1:0] datain;
    wire [WIDTH-1:0] dataout;

    // 实例化被测模块
    non_stall_pipeline nsp (
        .clk(clk),
        .datain(datain),
        .dataout(dataout)
    );
    
    always begin
        #5 clk = ~clk;
    end

    // 初始激励
    initial begin
    $dumpfile("nsp.vcd");
    $dumpvars(0, tb_non_stall_pipeline);

	$monitor("Time = %0t | datain = %h | dataout = %h", $time, datain, dataout);
	clk = 0;
	datain = 0;

	#10 datain = 100'hDEADBEEFCAFEBABEDEADBEEF0;
	#10 datain = 100'h0000000000000000000000000;
	#10 datain = 100'hFFFFFFFFFFFFFFFFFFFFFFFFF;
	#10 datain = 100'h123456789ABCDEF0123456789;

	#50 $finish;
	end

endmodule

example/nsp.vcd
$date
	Wed Mar 04 09:43:45 2026
$end
$version
	Icarus Verilog
$end
$timescale
	1ps
$end
$scope module tb_non_stall_pipeline $end
$var wire 100 ! dataout [99:0] $end
$var parameter 32 " WIDTH $end
$var reg 1 # clk $end
$var reg 100 $ datain [99:0] $end
$scope module nsp $end
$var wire 1 # clk $end
$var wire 100 % datain [99:0] $end
$var wire 100 & dataout [99:0] $end
$var parameter 32 ' WIDTH $end
$var reg 100 ( pipe1_data [99:0] $end
$var reg 100 ) pipe2_data [99:0] $end
$var reg 100 * pipe3_data [99:0] $end
$upscope $end
$upscope $end
$enddefinitions $end
$comment Show the parameter values. $end
$dumpall
b1100100 '
b1100100 "
$end
#0
$dumpvars
bx *
bx )
bx (
bx &
b0 %
b0 $
0#
bx !
$end
#5000
b0 (
1#
#10000
0#
b1101111010101101101111101110111111001010111111101011101010111110110111101010110110111110111011110000 $
b1101111010101101101111101110111111001010111111101011101010111110110111101010110110111110111011110000 %
#15000
b0 )
b1101111010101101101111101110111111001010111111101011101010111110110111101010110110111110111011110000 (
1#
#20000
0#
b0 $
b0 %
#25000
b0 (
b1101111010101101101111101110111111001010111111101011101010111110110111101010110110111110111011110000 )
b0 !
b0 &
b0 *
1#
#30000
0#
b1111111111111111111111111111111111111111111111111111111111111111111111111111111111111111111111111111 $
b1111111111111111111111111111111111111111111111111111111111111111111111111111111111111111111111111111 %
#35000
b1101111010101101101111101110111111001010111111101011101010111110110111101010110110111110111011110000 !
b1101111010101101101111101110111111001010111111101011101010111110110111101010110110111110111011110000 &
b1101111010101101101111101110111111001010111111101011101010111110110111101010110110111110111011110000 *
b0 )
b1111111111111111111111111111111111111111111111111111111111111111111111111111111111111111111111111111 (
1#
#40000
0#
b1001000110100010101100111100010011010101111001101111011110000000100100011010001010110011110001001 $
b1001000110100010101100111100010011010101111001101111011110000000100100011010001010110011110001001 %
#45000
b1001000110100010101100111100010011010101111001101111011110000000100100011010001010110011110001001 (
b1111111111111111111111111111111111111111111111111111111111111111111111111111111111111111111111111111 )
b0 !
b0 &
b0 *
1#
#50000
0#
#55000
b1111111111111111111111111111111111111111111111111111111111111111111111111111111111111111111111111111 !
b1111111111111111111111111111111111111111111111111111111111111111111111111111111111111111111111111111 &
b1111111111111111111111111111111111111111111111111111111111111111111111111111111111111111111111111111 *
b1001000110100010101100111100010011010101111001101111011110000000100100011010001010110011110001001 )
1#
#60000
0#
#65000
b1001000110100010101100111100010011010101111001101111011110000000100100011010001010110011110001001 !
b1001000110100010101100111100010011010101111001101111011110000000100100011010001010110011110001001 &
b1001000110100010101100111100010011010101111001101111011110000000100100011010001010110011110001001 *
1#
