single-cycle-cpu/definition.vh
`define PR_DATA_WIDTH 100 // pipepline register width

// NPCOp
`define NPC_PLUS4  2'b00
`define NPC_BRANCH 2'b01
`define NPC_JAL   2'b10
`define NPC_JALR   2'b11

// EXTOp
`define EXT_ITYPE  3'b000
`define EXT_STYPE  3'b001
`define EXT_BTYPE  3'b010
`define EXT_UTYPE  3'b011
`define EXT_JTYPE  3'b100
`define EXT_SHAMT  3'b101

// ALUOp: 00xxx算术逻辑, 01xxx移位比较, 10xxx分支
`define ALUOp_add  5'b00000
`define ALUOp_sub  5'b00001
`define ALUOp_and  5'b00010
`define ALUOp_or   5'b00011
`define ALUOp_xor  5'b00100

`define ALUOp_sll  5'b01000
`define ALUOp_srl  5'b01001
`define ALUOp_sra  5'b01010
`define ALUOp_slt  5'b01100
`define ALUOp_sltu 5'b01101

`define ALUOp_beq  5'b10000
`define ALUOp_bne  5'b10001
`define ALUOp_blt  5'b10100
`define ALUOp_bge  5'b10101
`define ALUOp_bltu 5'b10110
`define ALUOp_bgeu 5'b10111

// DMType
`define DM_WORD    3'b000 // lw, sw
`define DM_HALF    3'b001 // lh, sh
`define DM_HALFU   3'b010 // lhu
`define DM_BYTE    3'b011 // lb, sb
`define DM_BYTEU   3'b100 // lbu

// WDSel
`define WD_ALU     3'b000
`define WD_MEM     3'b001 // load
`define WD_PC4     3'b010 // jal, jalr
`define WD_IMM     3'b011 // lui
`define WD_PCIMM   3'b100 // auipc

stallable_pipeline.v
`include "definition.vh"

// ============================================================
// 五级流水线 RISC-V CPU（仅支持 I0: LUI/AUIPC 和 I3: ADDI/SLTI/SLTIU/XORI/ORI/ANDI/SLLI/SRLI/SRAI）
// 接口保持与框架一致：datain[31:0] 为指令，dataout[31:0] 为 WB 写回值，dataout[36:32] 为 rd
// 五级：IF → ID → EX → MEM → WB
// ============================================================
module stallable_pipeline #(
	parameter WIDTH = `PR_DATA_WIDTH
)(
	input 			clk,
	input			rst,
	input			validin,
	input [WIDTH-1:0]	datain,
	input 			out_allow,
	output			validout,
	output[WIDTH-1:0]	dataout
);

// ============================================================
// 寄存器堆（32个32位寄存器）
// ============================================================
reg [31:0] regfile [31:0];
integer _i;
always @(posedge clk or posedge rst) begin
	if (rst) begin
		for (_i = 0; _i < 32; _i = _i + 1)
			regfile[_i] <= _i;  // 复位时初始化为寄存器下标
	end
end

// ============================================================
// 流水线级间寄存器有效位
// ============================================================
reg  pipe1_valid; // IF
reg  pipe2_valid; // ID
reg  pipe3_valid; // EX
reg  pipe4_valid; // MEM
reg  pipe5_valid; // WB

// ============================================================
// IF 级（Stage 1）：接收指令（datain[31:0]）和 PC（datain[63:32]）
// ============================================================
// IF/ID 流水线寄存器
reg [31:0] if_id_instr;
reg [31:0] if_id_pc;

wire pipe1_allowin;
wire pipe1_ready_go;
wire pipe1_to_pipe2_valid;

assign pipe1_ready_go      = 1'b1;
assign pipe1_allowin       = !pipe1_valid || (pipe1_ready_go && pipe2_allowin);
assign pipe1_to_pipe2_valid = pipe1_valid && pipe1_ready_go;

always @(posedge clk or posedge rst) begin
	if (rst) begin
		pipe1_valid  <= 1'b0;
		if_id_instr  <= 32'b0;
		if_id_pc     <= 32'b0;
	end else begin
		if (pipe1_allowin)
			pipe1_valid <= validin;
		if (validin && pipe1_allowin) begin
			if_id_instr <= datain[31:0];
			if_id_pc    <= datain[63:32];
		end
	end
end

// ============================================================
// ID 级（Stage 2）：译码、立即数扩展、读寄存器
// ============================================================
// 指令字段解码
wire [6:0]  id_op     = if_id_instr[6:0];
wire [4:0]  id_rd     = if_id_instr[11:7];
wire [2:0]  id_funct3 = if_id_instr[14:12];
wire [4:0]  id_rs1    = if_id_instr[19:15];
wire [6:0]  id_funct7 = if_id_instr[31:25];
wire [4:0]  id_shamt  = if_id_instr[24:20];
wire [11:0] id_iimm   = if_id_instr[31:20];
wire [19:0] id_uimm   = if_id_instr[31:12];

// 指令类型识别
wire id_itype_r = (id_op == 7'b0010011); // ADDI/SLTI/SLTIU/XORI/ORI/ANDI/SLLI/SRLI/SRAI
wire id_lui     = (id_op == 7'b0110111); // LUI
wire id_auipc   = (id_op == 7'b0010111); // AUIPC

// I3 移位指令（使用 shamt 而非完整立即数）
wire id_slli  = id_itype_r & (id_funct3 == 3'b001);
wire id_srli  = id_itype_r & (id_funct3 == 3'b101) & (id_funct7[5] == 1'b0);
wire id_srai  = id_itype_r & (id_funct3 == 3'b101) & (id_funct7[5] == 1'b1);
wire id_shift = id_slli | id_srli | id_srai;

// 立即数扩展
reg [31:0] id_imm;
always @(*) begin
	if (id_lui || id_auipc)
		id_imm = {id_uimm, 12'b0};            // U型立即数
	else if (id_shift)
		id_imm = {27'b0, id_shamt};            // 移位量
	else
		id_imm = {{20{id_iimm[11]}}, id_iimm}; // I型符号扩展
end

// ALUOp 编码（与 alu.v 保持一致）
reg [4:0] id_aluop;
always @(*) begin
	if (id_lui)
		id_aluop = 5'b00011; // add（LUI: 0+imm，A选0）
	else if (id_auipc)
		id_aluop = 5'b00011; // add（AUIPC: PC+imm）
	else begin
		case (id_funct3)
			3'b000: id_aluop = 5'b00011; // addi: add
			3'b010: id_aluop = 5'b00111; // slti: slt
			3'b011: id_aluop = 5'b01010; // sltiu: sltu
			3'b100: id_aluop = 5'b01001; // xori: xor
			3'b110: id_aluop = 5'b01011; // ori: or
			3'b111: id_aluop = 5'b01111; // andi: and
			3'b001: id_aluop = 5'b00001; // slli: sll
			3'b101: id_aluop = id_funct7[5] ? 5'b00101 : 5'b00010; // srai/srli
			default: id_aluop = 5'b00000;
		endcase
	end
end

// RegWrite 控制（上述所有指令均写寄存器）
wire id_regwrite = id_itype_r | id_lui | id_auipc;

// ALUSrcA：LUI 时 A=0，AUIPC 时 A=PC，其余 A=RS1
// 用 [1:0] 编码：00=RS1值，01=PC，10=0
wire [1:0] id_alusrca = id_lui   ? 2'b10 :
                        id_auipc ? 2'b01 :
                                   2'b00;

// 读寄存器（LUI/AUIPC 不需要读 rs1，但为简单起见还是读）
wire [31:0] id_rdata1 = (id_rs1 == 5'b0) ? 32'b0 : regfile[id_rs1];

// ID/EX 流水线寄存器
reg [31:0] id_ex_pc;
reg [31:0] id_ex_rdata1;
reg [31:0] id_ex_imm;
reg [4:0]  id_ex_aluop;
reg [1:0]  id_ex_alusrca;
reg [4:0]  id_ex_rd;
reg        id_ex_regwrite;

wire pipe2_allowin;
wire pipe2_ready_go;
wire pipe2_to_pipe3_valid;

assign pipe2_ready_go      = 1'b1;
assign pipe2_allowin       = !pipe2_valid || (pipe2_ready_go && pipe3_allowin);
assign pipe2_to_pipe3_valid = pipe2_valid && pipe2_ready_go;

always @(posedge clk or posedge rst) begin
	if (rst) begin
		pipe2_valid      <= 1'b0;
		id_ex_pc         <= 32'b0;
		id_ex_rdata1     <= 32'b0;
		id_ex_imm        <= 32'b0;
		id_ex_aluop      <= 5'b0;
		id_ex_alusrca    <= 2'b0;
		id_ex_rd         <= 5'b0;
		id_ex_regwrite   <= 1'b0;
	end else begin
		if (pipe2_allowin)
			pipe2_valid <= pipe1_to_pipe2_valid;
		if (pipe1_to_pipe2_valid && pipe2_allowin) begin
			id_ex_pc       <= if_id_pc;
			id_ex_rdata1   <= id_rdata1;
			id_ex_imm      <= id_imm;
			id_ex_aluop    <= id_aluop;
			id_ex_alusrca  <= id_alusrca;
			id_ex_rd       <= id_rd;
			id_ex_regwrite <= id_regwrite;
		end
	end
end

// ============================================================
// EX 级（Stage 3）：ALU 运算
// ============================================================
// ALU A 端选择
wire [31:0] ex_alu_a = (id_ex_alusrca == 2'b10) ? 32'b0         // LUI: A=0
                     : (id_ex_alusrca == 2'b01) ? id_ex_pc       // AUIPC: A=PC
                     :                             id_ex_rdata1;  // 其余: A=RS1

wire [31:0] ex_alu_b = id_ex_imm; // B 端始终为立即数

// ALU 运算（内联，与 alu.v 逻辑一致）
reg [31:0] ex_aluout;
always @(*) begin
	case (id_ex_aluop)
		5'b00001: ex_aluout = ex_alu_a << ex_alu_b[4:0];                            // sll
		5'b00010: ex_aluout = ex_alu_a >> ex_alu_b[4:0];                            // srl
		5'b00101: ex_aluout = $signed(ex_alu_a) >>> ex_alu_b[4:0];                  // sra
		5'b00011: ex_aluout = ex_alu_a + ex_alu_b;                                  // add
		5'b01111: ex_aluout = ex_alu_a & ex_alu_b;                                  // and
		5'b01011: ex_aluout = ex_alu_a | ex_alu_b;                                  // or
		5'b01001: ex_aluout = ex_alu_a ^ ex_alu_b;                                  // xor
		5'b00111: ex_aluout = ($signed(ex_alu_a) < $signed(ex_alu_b)) ? 32'd1 : 32'd0; // slt
		5'b01010: ex_aluout = (ex_alu_a < ex_alu_b) ? 32'd1 : 32'd0;               // sltu
		default:  ex_aluout = 32'b0;
	endcase
end

// EX/MEM 流水线寄存器
reg [31:0] ex_mem_aluout;
reg [4:0]  ex_mem_rd;
reg        ex_mem_regwrite;

wire pipe3_allowin;
wire pipe3_ready_go;
wire pipe3_to_pipe4_valid;

assign pipe3_ready_go      = 1'b1;
assign pipe3_allowin       = !pipe3_valid || (pipe3_ready_go && pipe4_allowin);
assign pipe3_to_pipe4_valid = pipe3_valid && pipe3_ready_go;

always @(posedge clk or posedge rst) begin
	if (rst) begin
		pipe3_valid        <= 1'b0;
		ex_mem_aluout      <= 32'b0;
		ex_mem_rd          <= 5'b0;
		ex_mem_regwrite    <= 1'b0;
	end else begin
		if (pipe3_allowin)
			pipe3_valid <= pipe2_to_pipe3_valid;
		if (pipe2_to_pipe3_valid && pipe3_allowin) begin
			ex_mem_aluout   <= ex_aluout;
			ex_mem_rd       <= id_ex_rd;
			ex_mem_regwrite <= id_ex_regwrite;
		end
	end
end

// ============================================================
// MEM 级（Stage 4）：本批指令无内存读写，直接传递
// ============================================================
// MEM/WB 流水线寄存器
reg [31:0] mem_wb_result;
reg [4:0]  mem_wb_rd;
reg        mem_wb_regwrite;

wire pipe4_allowin;
wire pipe4_ready_go;
wire pipe4_to_pipe5_valid;

assign pipe4_ready_go      = 1'b1;
assign pipe4_allowin       = !pipe4_valid || (pipe4_ready_go && pipe5_allowin);
assign pipe4_to_pipe5_valid = pipe4_valid && pipe4_ready_go;

always @(posedge clk or posedge rst) begin
	if (rst) begin
		pipe4_valid        <= 1'b0;
		mem_wb_result      <= 32'b0;
		mem_wb_rd          <= 5'b0;
		mem_wb_regwrite    <= 1'b0;
	end else begin
		if (pipe4_allowin)
			pipe4_valid <= pipe3_to_pipe4_valid;
		if (pipe3_to_pipe4_valid && pipe4_allowin) begin
			mem_wb_result   <= ex_mem_aluout;
			mem_wb_rd       <= ex_mem_rd;
			mem_wb_regwrite <= ex_mem_regwrite;
		end
	end
end

// ============================================================
// WB 级（Stage 5）：写回寄存器堆，输出结果
// ============================================================
wire pipe5_allowin;
wire pipe5_ready_go;

assign pipe5_ready_go = 1'b1;
assign pipe5_allowin  = !pipe5_valid || (pipe5_ready_go && out_allow);

always @(posedge clk or posedge rst) begin
	if (rst) begin
		pipe5_valid <= 1'b0;
	end else begin
		if (pipe5_allowin)
			pipe5_valid <= pipe4_to_pipe5_valid;
	end
end

// 写回寄存器堆（同步写，WB级有效且RegWrite有效且rd非0）
always @(posedge clk) begin
	if (!rst && pipe5_valid && mem_wb_regwrite && (mem_wb_rd != 5'b0))
		regfile[mem_wb_rd] <= mem_wb_result;
end

// ============================================================
// 输出：validout 和 dataout
// dataout[31:0]  = WB 写回值（ALU 结果）
// dataout[36:32] = rd（目标寄存器）
// dataout[37]    = RegWrite
// 其余位为 0
// ============================================================
assign validout       = pipe5_valid && pipe5_ready_go;
assign dataout        = {{(WIDTH-38){1'b0}}, mem_wb_regwrite, mem_wb_rd, mem_wb_result};

endmodule

tb_stallable_pipeline.v
`timescale 1ns / 1ps
`include "definition.vh"

// ============================================================
// 测试 I0 和 I3 指令（无数据冒险序列）
// datain[31:0]  = RISC-V 32位指令
// datain[63:32] = 当前指令的 PC 值（用于 AUIPC）
// dataout[31:0] = WB 写回值
// dataout[36:32]= rd（目标寄存器）
// dataout[37]   = RegWrite（写回有效）
//
// 指令编码说明（RISC-V）：
//   LUI   rd, imm   : {imm[31:12], rd, 7'b0110111}
//   AUIPC rd, imm   : {imm[31:12], rd, 7'b0010111}
//   ADDI  rd,rs1,imm: {imm[11:0], rs1, 3'b000, rd, 7'b0010011}
//   SLTI  rd,rs1,imm: {imm[11:0], rs1, 3'b010, rd, 7'b0010011}
//   SLTIU rd,rs1,imm: {imm[11:0], rs1, 3'b011, rd, 7'b0010011}
//   XORI  rd,rs1,imm: {imm[11:0], rs1, 3'b100, rd, 7'b0010011}
//   ORI   rd,rs1,imm: {imm[11:0], rs1, 3'b110, rd, 7'b0010011}
//   ANDI  rd,rs1,imm: {imm[11:0], rs1, 3'b111, rd, 7'b0010011}
//   SLLI  rd,rs1,shamt: {7'b0000000, shamt, rs1, 3'b001, rd, 7'b0010011}
//   SRLI  rd,rs1,shamt: {7'b0000000, shamt, rs1, 3'b101, rd, 7'b0010011}
//   SRAI  rd,rs1,shamt: {7'b0100000, shamt, rs1, 3'b101, rd, 7'b0010011}
// ============================================================
module tb_stallable_pipeline;

    // 参数声明
    parameter WIDTH = `PR_DATA_WIDTH;

    // 信号声明
    reg         	clk;
    reg         	rst;
    reg         	validin;
    reg [WIDTH-1:0] 	datain;
    reg         	out_allow;
    wire        	validout;
    wire [WIDTH-1:0] 	dataout;

    // 拆解输出字段
    wire [31:0] wb_result   = dataout[31:0];
    wire [4:0]  wb_rd       = dataout[36:32];
    wire        wb_regwrite = dataout[37];

    //---------------------------------------------------------------------
    // 实例化被测模块
    //---------------------------------------------------------------------
    stallable_pipeline sp(
        .clk(clk),
        .rst(rst),
        .validin(validin),
        .datain(datain),
        .out_allow(out_allow),
        .validout(validout),
        .dataout(dataout)
    );

    always begin
    	forever #5 clk = ~clk;
        if (clk == 1)
        begin
            counter = counter + 1;
        end
    end

    integer counter = 0;

    // 辅助任务：发送一条指令
    task send_instr;
        input [31:0] instr;
        input [31:0] pc;
        begin
            datain   = {{(WIDTH-64){1'b0}}, pc, instr};
            validin  = 1'b1;
            #10;
            validin  = 1'b0;
        end
    endtask

    initial begin
        // 初始化信号
        clk      = 0;
        rst      = 1'b1;
        validin  = 1'b0;
        datain   = {WIDTH{1'b0}};
        out_allow = 1'b1;

	    // 打开 VCD 波形记录
        $dumpfile("sp.vcd");
        $dumpvars(0, tb_stallable_pipeline);

        #10;
        rst = 1'b0; // 释放复位

        //--------------------------------------------------
        // 场景一：I0 指令 — LUI 和 AUIPC（无冒险）
        //--------------------------------------------------
        $display("=== 场景一：I0 指令（LUI / AUIPC）===");

        // LUI x1, 0xABCDE  => x1 = 0xABCDE000
        // 编码: {20'hABCDE, 5'd1, 7'b0110111}
        send_instr({20'hABCDE, 5'd1, 7'b0110111}, 32'h00000000);
        #40; // 等待流水线完成，再发下一条（无冒险）

        // AUIPC x2, 0x10   => x2 = PC(0x100) + 0x10000 = 0x10100
        // 编码: {20'h00010, 5'd2, 7'b0010111}
        send_instr({20'h00010, 5'd2, 7'b0010111}, 32'h00000100);
        #40;

        //--------------------------------------------------
        // 场景二：I3 指令 — 算术/逻辑/移位立即数（无冒险）
        //--------------------------------------------------
        $display("=== 场景二：I3 指令（ADDI/SLTI/SLTIU/XORI/ORI/ANDI）===");

        // ADDI x3, x0, 100  => x3 = 0 + 100 = 100 = 0x64
        // 编码: {12'd100, 5'd0, 3'b000, 5'd3, 7'b0010011}
        send_instr({12'd100, 5'd0, 3'b000, 5'd3, 7'b0010011}, 32'h00000200);
        #40;

        // SLTI x4, x0, 5    => x4 = (0 < 5) = 1
        // 编码: {12'd5, 5'd0, 3'b010, 5'd4, 7'b0010011}
        send_instr({12'd5, 5'd0, 3'b010, 5'd4, 7'b0010011}, 32'h00000204);
        #40;

        // SLTIU x5, x0, 1   => x5 = (0 <u 1) = 1
        // 编码: {12'd1, 5'd0, 3'b011, 5'd5, 7'b0010011}
        send_instr({12'd1, 5'd0, 3'b011, 5'd5, 7'b0010011}, 32'h00000208);
        #40;

        // XORI x6, x0, 12'hFFF  => x6 = 0 ^ 0xFFFFFFFF = 0xFFFFFFFF
        // 编码: {12'hFFF, 5'd0, 3'b100, 5'd6, 7'b0010011}
        send_instr({12'hFFF, 5'd0, 3'b100, 5'd6, 7'b0010011}, 32'h0000020C);
        #40;

        // ORI  x7, x0, 12'hA5   => x7 = 0 | 0xA5 = 0xA5
        // 编码: {12'hA5, 5'd0, 3'b110, 5'd7, 7'b0010011}
        send_instr({12'hA5, 5'd0, 3'b110, 5'd7, 7'b0010011}, 32'h00000210);
        #40;

        // ANDI x8, x0, 12'hFF   => x8 = 0 & 0xFF = 0
        // 编码: {12'hFF, 5'd0, 3'b111, 5'd8, 7'b0010011}
        send_instr({12'hFF, 5'd0, 3'b111, 5'd8, 7'b0010011}, 32'h00000214);
        #40;

        $display("=== 场景三：I3 移位指令（SLLI/SRLI/SRAI）===");

        // SLLI x9, x0, 4   => x9 = 0 << 4 = 0（使用 x0 结果平凡，只验证控制路径）
        // 编码: {7'b0000000, 5'd4, 5'd0, 3'b001, 5'd9, 7'b0010011}
        send_instr({7'b0000000, 5'd4, 5'd0, 3'b001, 5'd9, 7'b0010011}, 32'h00000218);
        #40;

        // SRLI x10, x0, 2  => x10 = 0 >> 2 = 0
        // 编码: {7'b0000000, 5'd2, 5'd0, 3'b101, 5'd10, 7'b0010011}
        send_instr({7'b0000000, 5'd2, 5'd0, 3'b101, 5'd10, 7'b0010011}, 32'h0000021C);
        #40;

        // SRAI x11, x0, 1  => x11 = 0 >>> 1 = 0
        // 编码: {7'b0100000, 5'd1, 5'd0, 3'b101, 5'd11, 7'b0010011}
        send_instr({7'b0100000, 5'd1, 5'd0, 3'b101, 5'd11, 7'b0010011}, 32'h00000220);
        #40;

        //--------------------------------------------------
        // 场景四：out_allow 被拉低（阻塞 WB 级），观察流水线暂停
        //--------------------------------------------------
        $display("=== 场景四：out_allow=0 阻塞 WB 级 ===");

        send_instr({20'h12345, 5'd12, 7'b0110111}, 32'h00000300); // LUI x12, 0x12345
        out_allow = 1'b0;
        #40;
        $display("Resuming: out_allow=1");
        out_allow = 1'b1;
        #50;

        //--------------------------------------------------
        // 场景五：复位清空流水线
        //--------------------------------------------------
        $display("=== 场景五：复位 ===");
        rst = 1'b1;
        #20;
        rst = 1'b0;
        #50;

        $finish;
    end

    // 监视 WB 输出
    always @(posedge clk) begin
        if (validout && wb_regwrite)
            $display("[WB] t=%0t  rd=x%0d  result=0x%08h", $time, wb_rd, wb_result);
    end

endmodule

sp.vcd
$date
	Tue Mar 10 00:13:02 2026
$end
$version
	Icarus Verilog
$end
$timescale
	1ps
$end
$scope module tb_stallable_pipeline $end
$var wire 32 ! wb_result [31:0] $end
$var wire 1 " wb_regwrite $end
$var wire 5 # wb_rd [4:0] $end
$var wire 1 $ validout $end
$var wire 100 % dataout [99:0] $end
$var parameter 32 & WIDTH $end
$var reg 1 ' clk $end
$var reg 100 ( datain [99:0] $end
$var reg 1 ) out_allow $end
$var reg 1 * rst $end
$var reg 1 + validin $end
$var integer 32 , counter [31:0] $end
$scope module sp $end
$var wire 1 ' clk $end
$var wire 100 - datain [99:0] $end
$var wire 32 . ex_alu_b [31:0] $end
$var wire 1 / id_regwrite $end
$var wire 1 0 id_shift $end
$var wire 1 1 id_slli $end
$var wire 1 2 id_srai $end
$var wire 1 3 id_srli $end
$var wire 1 ) out_allow $end
$var wire 1 4 pipe1_allowin $end
$var wire 1 5 pipe1_ready_go $end
$var wire 1 6 pipe1_to_pipe2_valid $end
$var wire 1 7 pipe2_allowin $end
$var wire 1 8 pipe2_ready_go $end
$var wire 1 9 pipe2_to_pipe3_valid $end
$var wire 1 : pipe3_allowin $end
$var wire 1 ; pipe3_ready_go $end
$var wire 1 < pipe3_to_pipe4_valid $end
$var wire 1 = pipe4_allowin $end
$var wire 1 > pipe4_ready_go $end
$var wire 1 ? pipe4_to_pipe5_valid $end
$var wire 1 @ pipe5_allowin $end
$var wire 1 A pipe5_ready_go $end
$var wire 1 * rst $end
$var wire 1 + validin $end
$var wire 1 $ validout $end
$var wire 20 B id_uimm [19:0] $end
$var wire 5 C id_shamt [4:0] $end
$var wire 5 D id_rs1 [4:0] $end
$var wire 32 E id_rdata1 [31:0] $end
$var wire 5 F id_rd [4:0] $end
$var wire 7 G id_op [6:0] $end
$var wire 1 H id_lui $end
$var wire 1 I id_itype_r $end
$var wire 12 J id_iimm [11:0] $end
$var wire 7 K id_funct7 [6:0] $end
$var wire 3 L id_funct3 [2:0] $end
$var wire 1 M id_auipc $end
$var wire 2 N id_alusrca [1:0] $end
$var wire 32 O ex_alu_a [31:0] $end
$var wire 100 P dataout [99:0] $end
$var parameter 32 Q WIDTH $end
$var reg 32 R ex_aluout [31:0] $end
$var reg 32 S ex_mem_aluout [31:0] $end
$var reg 5 T ex_mem_rd [4:0] $end
$var reg 1 U ex_mem_regwrite $end
$var reg 5 V id_aluop [4:0] $end
$var reg 5 W id_ex_aluop [4:0] $end
$var reg 2 X id_ex_alusrca [1:0] $end
$var reg 32 Y id_ex_imm [31:0] $end
$var reg 32 Z id_ex_pc [31:0] $end
$var reg 5 [ id_ex_rd [4:0] $end
$var reg 32 \ id_ex_rdata1 [31:0] $end
$var reg 1 ] id_ex_regwrite $end
$var reg 32 ^ id_imm [31:0] $end
$var reg 32 _ if_id_instr [31:0] $end
$var reg 32 ` if_id_pc [31:0] $end
$var reg 5 a mem_wb_rd [4:0] $end
$var reg 1 b mem_wb_regwrite $end
$var reg 32 c mem_wb_result [31:0] $end
$var reg 1 d pipe1_valid $end
$var reg 1 e pipe2_valid $end
$var reg 1 f pipe3_valid $end
$var reg 1 g pipe4_valid $end
$var reg 1 h pipe5_valid $end
$var integer 32 i _i [31:0] $end
$upscope $end
$scope task send_instr $end
$var reg 32 j instr [31:0] $end
$var reg 32 k pc [31:0] $end
$upscope $end
$upscope $end
$enddefinitions $end
$comment Show the parameter values. $end
$dumpall
b1100100 Q
b1100100 &
$end
#0
$dumpvars
bx k
bx j
b100000 i
0h
0g
0f
0e
0d
b0 c
0b
b0 a
b0 `
b0 _
b0 ^
0]
b0 \
b0 [
b0 Z
b0 Y
b0 X
b0 W
b11 V
0U
b0 T
b0 S
b0 R
b0 P
b0 O
b0 N
0M
b0 L
b0 K
b0 J
0I
0H
b0 G
b0 F
b0 E
b0 D
b0 C
b0 B
1A
1@
0?
1>
1=
0<
1;
1:
09
18
17
06
15
14
03
02
01
00
0/
b0 .
b0 -
b0 ,
0+
1*
1)
b0 (
0'
b0 %
0$
b0 #
0"
b0 !
$end
#5000
b100000 i
1'
#10000
0'
1+
b10101011110011011110000010110111 (
b10101011110011011110000010110111 -
b0 k
b10101011110011011110000010110111 j
0*
#15000
1/
b10 N
b11011 E
b10101011110011011110000000000000 ^
1H
b110111 G
b1 F
b110 L
b11011 D
b1010101 K
b11100 C
b101010111100 J
b10101011110011011110 B
16
b10101011110011011110000010110111 _
1d
1'
#20000
0'
0+
#25000
b10101011110011011110000000000000 R
19
06
1]
b1 [
b10 X
b11 W
b10101011110011011110000000000000 .
b10101011110011011110000000000000 Y
b11011 \
1e
0d
1'
#30000
0'
#35000
09
1<
0e
1U
b1 T
b10101011110011011110000000000000 S
1f
1'
#40000
0'
#45000
1"
b1 #
b10101011110011011110000000000000 !
1?
0<
1b
b1 a
b10000110101011110011011110000000000000 %
b10000110101011110011011110000000000000 P
b10101011110011011110000000000000 c
1g
0f
1'
#50000
0'
#55000
0?
1$
0g
1h
1'
#60000
0'
1+
b10000000000000000000000010000000100010111 (
b10000000000000000000000010000000100010111 -
b100000000 k
b10000000100010111 j
#65000
b1 N
b10 E
b10000000000000000 ^
0$
0H
1M
b10111 G
b10 F
b0 L
b10 D
b0 K
b0 C
b0 J
b10000 B
16
0h
b100000000 `
b10000000100010111 _
1d
1'
#70000
0'
0+
#75000
06
b100000000 O
b10000000100000000 R
19
0d
b10 [
b1 X
b10000000000000000 .
b10000000000000000 Y
b10 \
b100000000 Z
1e
1'
#80000
0'
#85000
1<
09
b10 T
b10000000100000000 S
1f
0e
1'
#90000
0'
#95000
0<
b10 #
b10000000100000000 !
1?
0f
b10 a
b10001000000000000000010000000100000000 %
b10001000000000000000010000000100000000 P
b10000000100000000 c
1g
1'
#100000
0'
#105000
1$
0?
1h
0g
1'
#110000
0'
1+
b100000000000000110010000000000000110010011 (
b100000000000000110010000000000000110010011 -
b1000000000 k
b110010000000000000110010011 j
#115000
b0 N
1/
b1100100 ^
b0 E
1I
0M
b10011 G
b11 F
b0 D
b11 K
b100 C
b1100100 J
b110010000000000 B
16
0$
b1000000000 `
b110010000000000000110010011 _
1d
0h
1'
#120000
0'
0+
#125000
b0 O
b1100100 R
19
06
b11 [
b0 X
b1100100 .
b1100100 Y
b0 \
b1000000000 Z
1e
0d
1'
#130000
0'
#135000
09
1<
0e
b11 T
b1100100 S
1f
1'
#140000
0'
#145000
b11 #
b1100100 !
1?
0<
b11 a
b10001100000000000000000000000001100100 %
b10001100000000000000000000000001100100 P
b1100100 c
1g
0f
1'
#150000
0'
#155000
0?
1$
0g
1h
1'
#160000
0'
1+
b100000010000000000010100000010001000010011 (
b100000010000000000010100000010001000010011 -
b1000000100 k
b10100000010001000010011 j
#165000
b111 V
b101 ^
0$
b100 F
b10 L
b0 K
b101 C
b101 J
b10100000010 B
16
0h
b1000000100 `
b10100000010001000010011 _
1d
1'
#170000
0'
0+
#175000
06
b1 R
19
0d
b100 [
b111 W
b101 .
b101 Y
b1000000100 Z
1e
1'
#180000
0'
#185000
1<
09
b100 T
b1 S
1f
0e
1'
#190000
0'
#195000
0<
b100 #
b1 !
1?
0f
b100 a
b10010000000000000000000000000000000001 %
b10010000000000000000000000000000000001 P
b1 c
1g
1'
#200000
0'
#205000
1$
0?
1h
0g
1'
#210000
0'
1+
b100000100000000000000100000011001010010011 (
b100000100000000000000100000011001010010011 -
b1000001000 k
b100000011001010010011 j
#215000
b1010 V
b1 ^
b101 F
b11 L
b1 C
b1 J
b100000011 B
16
0$
b1000001000 `
b100000011001010010011 _
1d
0h
1'
#220000
0'
0+
#225000
19
06
b101 [
b1010 W
b1 .
b1 Y
b1000001000 Z
1e
0d
1'
#230000
0'
#235000
09
1<
0e
b101 T
1f
1'
#240000
0'
#245000
b101 #
1?
0<
b10010100000000000000000000000000000001 %
b10010100000000000000000000000000000001 P
b101 a
1g
0f
1'
#250000
0'
#255000
0?
1$
0g
1h
1'
#260000
0'
1+
b100000110011111111111100000100001100010011 (
b100000110011111111111100000100001100010011 -
b1000001100 k
b11111111111100000100001100010011 j
#265000
b1001 V
b11111111111111111111111111111111 ^
0$
b110 F
b100 L
b1111111 K
b11111 C
b111111111111 J
b11111111111100000100 B
16
0h
b1000001100 `
b11111111111100000100001100010011 _
1d
1'
#270000
0'
0+
#275000
06
b11111111111111111111111111111111 R
19
0d
b110 [
b1001 W
b11111111111111111111111111111111 .
b11111111111111111111111111111111 Y
b1000001100 Z
1e
1'
#280000
0'
#285000
1<
09
b110 T
b11111111111111111111111111111111 S
1f
0e
1'
#290000
0'
#295000
0<
b110 #
b11111111111111111111111111111111 !
1?
0f
b110 a
b10011011111111111111111111111111111111 %
b10011011111111111111111111111111111111 P
b11111111111111111111111111111111 c
1g
1'
#300000
0'
#305000
1$
0?
1h
0g
1'
#310000
0'
1+
b100001000000001010010100000110001110010011 (
b100001000000001010010100000110001110010011 -
b1000010000 k
b1010010100000110001110010011 j
#315000
b1011 V
b10100101 ^
b111 F
b110 L
b101 K
b101 C
b10100101 J
b1010010100000110 B
16
0$
b1000010000 `
b1010010100000110001110010011 _
1d
0h
1'
#320000
0'
0+
#325000
b10100101 R
19
06
b111 [
b1011 W
b10100101 .
b10100101 Y
b1000010000 Z
1e
0d
1'
#330000
0'
#335000
09
1<
0e
b111 T
b10100101 S
1f
1'
#340000
0'
#345000
b111 #
b10100101 !
1?
0<
b111 a
b10011100000000000000000000000010100101 %
b10011100000000000000000000000010100101 P
b10100101 c
1g
0f
1'
#350000
0'
#355000
0?
1$
0g
1h
1'
#360000
0'
1+
b100001010000001111111100000111010000010011 (
b100001010000001111111100000111010000010011 -
b1000010100 k
b1111111100000111010000010011 j
#365000
b1111 V
b11111111 ^
0$
b1000 F
b111 L
b111 K
b11111 C
b11111111 J
b1111111100000111 B
16
0h
b1000010100 `
b1111111100000111010000010011 _
1d
1'
#370000
0'
0+
#375000
06
b0 R
19
0d
b1000 [
b1111 W
b11111111 .
b11111111 Y
b1000010100 Z
1e
1'
#380000
0'
#385000
1<
09
b1000 T
b0 S
1f
0e
1'
#390000
0'
#395000
0<
b1000 #
b0 !
1?
0f
b1000 a
b10100000000000000000000000000000000000 %
b10100000000000000000000000000000000000 P
b0 c
1g
1'
#400000
0'
#405000
1$
0?
1h
0g
1'
#410000
0'
1+
b100001100000000000010000000001010010010011 (
b100001100000000000010000000001010010010011 -
b1000011000 k
b10000000001010010010011 j
#415000
10
11
b1 V
b100 ^
b1001 F
b1 L
b0 K
b100 C
b100 J
b10000000001 B
16
0$
b1000011000 `
b10000000001010010010011 _
1d
0h
1'
#420000
0'
0+
#425000
19
06
b1001 [
b1 W
b100 .
b100 Y
b1000011000 Z
1e
0d
1'
#430000
0'
#435000
09
1<
0e
b1001 T
1f
1'
#440000
0'
#445000
b1001 #
1?
0<
b10100100000000000000000000000000000000 %
b10100100000000000000000000000000000000 P
b1001 a
1g
0f
1'
#450000
0'
#455000
0?
1$
0g
1h
1'
#460000
0'
1+
b100001110000000000001000000101010100010011 (
b100001110000000000001000000101010100010011 -
b1000011100 k
b1000000101010100010011 j
