single-cycle-cpu/definition.vh
`define PR_DATA_WIDTH 100 // pipepline register width

// NPCOp
`define NPC_PLUS4  2'b00
`define NPC_BRANCH 2'b01
`define NPC_JAL   2'b10
`define NPC_JALR   2'b11

// EXTOp
`define EXT_ITYPE  3'b000
`define EXT_STYPE  3'b001
`define EXT_BTYPE  3'b010
`define EXT_UTYPE  3'b011
`define EXT_JTYPE  3'b100
`define EXT_SHAMT  3'b101

// ALUOp: 00xxx算术逻辑, 01xxx移位比较, 10xxx分支
`define ALUOp_add  5'b00000
`define ALUOp_sub  5'b00001
`define ALUOp_and  5'b00010
`define ALUOp_or   5'b00011
`define ALUOp_xor  5'b00100

`define ALUOp_sll  5'b01000
`define ALUOp_srl  5'b01001
`define ALUOp_sra  5'b01010
`define ALUOp_slt  5'b01100
`define ALUOp_sltu 5'b01101

`define ALUOp_beq  5'b10000
`define ALUOp_bne  5'b10001
`define ALUOp_blt  5'b10100
`define ALUOp_bge  5'b10101
`define ALUOp_bltu 5'b10110
`define ALUOp_bgeu 5'b10111

// DMType
`define DM_WORD    3'b000 // lw, sw
`define DM_HALF    3'b001 // lh, sh
`define DM_HALFU   3'b010 // lhu
`define DM_BYTE    3'b011 // lb, sb
`define DM_BYTEU   3'b100 // lbu

// WDSel
`define WD_ALU     3'b000
`define WD_MEM     3'b001 // load
`define WD_PC4     3'b010 // jal, jalr
`define WD_IMM     3'b011 // lui
`define WD_PCIMM   3'b100 // auipc

temp/stallable_pipeline copy.v
`include "definition.vh"

module stallable_pipeline #(
	parameter WIDTH = `PR_DATA_WIDTH
)(
	input 			clk,
	input			rst,
	input			validin,
	input [WIDTH-1:0]	datain,
	input 			out_allow,
	output			validout,
	output[WIDTH-1:0]	dataout
);

	reg		pipe1_valid;
	reg [WIDTH-1:0]	pipe1_data;
	reg		pipe2_valid;
	reg [WIDTH-1:0]	pipe2_data;
	reg		pipe3_valid;
	reg [WIDTH-1:0]	pipe3_data;
	reg		pipe4_valid;
	reg [WIDTH-1:0]	pipe4_data;
	reg		pipe5_valid;
	reg [WIDTH-1:0]	pipe5_data;

	// pipeline stage1
	wire 	pipe1_allowin;
	wire	pipe1_ready_go;
	wire	pipe1_to_pipe2_valid;

	assign pipe1_ready_go = 1'b1; //此处恒设定为1，是用于阻塞的地方
	assign pipe1_allowin = !pipe1_valid || pipe1_ready_go && pipe2_allowin; // 优先级 ! > && > ||，pipe1无有效数据或者pipe1的数据已经准备往前走
	assign pipe1_to_pipe2_valid = pipe1_valid && pipe1_ready_go;

	always @(posedge clk ) begin
		if (rst) begin
			pipe1_valid <= 1'b0;
		end
		else if (pipe1_allowin) begin
			pipe1_valid <= validin;
		end

		if (validin && pipe1_allowin) begin
			pipe1_data <= datain;
		end
	end

	// pipeline stage2
	wire 	pipe2_allowin;
	wire	pipe2_ready_go;
	wire	pipe2_to_pipe3_valid;

	assign pipe2_ready_go = 1'b1; //此处恒设定为1，是用于阻塞的地方
	assign pipe2_allowin = !pipe2_valid || pipe2_ready_go && pipe3_allowin; // 优先级 ! > && > ||
	assign pipe2_to_pipe3_valid = pipe2_valid && pipe2_ready_go;

	always @(posedge clk ) begin
		if (rst) begin
			pipe2_valid <= 1'b0;
		end
		else if (pipe2_allowin) begin
			pipe2_valid <= pipe1_to_pipe2_valid;
		end

		if (pipe1_to_pipe2_valid && pipe2_allowin) begin
			pipe2_data <= pipe1_data;
		end
	end

	// pipeline stage3
	wire 	pipe3_allowin;
	wire	pipe3_ready_go;
	wire    pipe3_to_pipe4_valid;

	assign pipe3_ready_go = 1'b1; //此处恒设定为1，是用于阻塞的地方
	assign pipe3_allowin = !pipe3_valid || pipe3_ready_go && pipe4_allowin; // 优先级 ! > && > ||
	assign pipe3_to_pipe4_valid = pipe3_valid && pipe3_ready_go;

	always @(posedge clk ) begin
		if (rst) begin
			pipe3_valid <= 1'b0;
		end
		else if (pipe3_allowin) begin
			pipe3_valid <= pipe2_to_pipe3_valid; 
		end

		if (pipe2_to_pipe3_valid && pipe3_allowin) begin
			pipe3_data <= pipe2_data;
		end
	end

	// pipeline stage4
	wire 	pipe4_allowin;
	wire	pipe4_ready_go;

	assign pipe4_ready_go = 1'b1; 
	assign pipe4_allowin = !pipe4_valid || pipe4_ready_go && out_allow;

	always @(posedge clk ) begin
		if (rst) begin
			pipe4_valid <= 1'b0;
		end
		else if (pipe4_allowin) begin
			pipe4_valid <= pipe3_to_pipe4_valid;
		end

		if (pipe3_to_pipe4_valid && pipe4_allowin) begin
			pipe4_data <= pipe3_data;
		end
	end

	assign validout = pipe4_valid && pipe4_ready_go;
	assign dataout = pipe4_data;
endmodule

tb_stallable_pipeline.v
`timescale 1ns / 1ps
`include "definition.vh"

module tb_stallable_pipeline;

    // 参数声明
    parameter WIDTH = `PR_DATA_WIDTH;

    // 信号声明
    reg         	clk;
    reg         	rst;
    reg         	validin;
    reg [WIDTH-1:0] 	datain;
    reg         	out_allow;
    wire        	validout;
    wire [WIDTH-1:0] 	dataout;

    //---------------------------------------------------------------------
    // 实例化被测模块
    //---------------------------------------------------------------------
    stallable_pipeline sp(
        .clk(clk),
        .rst(rst),
        .validin(validin),
        .datain(datain),
        .out_allow(out_allow),
        .validout(validout),
        .dataout(dataout)
    );

    always begin
    	forever #5 clk = ~clk;
        if (clk == 1)
        begin
            counter = counter + 1;
        end
    end

    integer counter = 0;
    
    initial begin
        // 初始化信号
        clk = 0; // 设置初始值为 0
        rst = 1'b1;
        validin = 1'b0;
        datain = `PR_DATA_WIDTH'b0;
        out_allow = 1'b1;

	    // 打开 VCD 波形记录
        $dumpfile("sp.vcd");
        $dumpvars(0, tb_stallable_pipeline);

        #10 
        rst = 1'b0; // 释放复位

        //--------------------------------------------------
        // 场景一：正常传输
        //--------------------------------------------------
        //datain = `PR_DATA_WIDTH'hDEADBEEFDEADBEEFDEADBEEF0;
	    datain = {`PR_DATA_WIDTH{1'b1}};
        validin = 1'b1;
        #10 validin = 1'b0;

        #40; // 等待数据通过所有阶段

        //--------------------------------------------------
        // 场景二：out_allow 被拉低，阻塞 stage4
        //--------------------------------------------------
        $display("Blocking output by setting out_allow = 0");

        datain = 32'hCAFEBABE;
        validin = 1'b1;
        #10 validin = 1'b0;
        out_allow = 1'b0;
        #40; // 阻塞阶段4，观察 pipe4_valid 是否保持

        //--------------------------------------------------
        // 场景三：恢复输出并清空流水线
        //--------------------------------------------------
        $display("Resuming output by setting out_allow = 1");
        out_allow = 1'b1;
	    #40

        //--------------------------------------------------
        // 场景四：插入复位信号
        //--------------------------------------------------
        $display("Asserting reset...");
        rst = 1'b1;

        #20 rst = 1'b0;

        #50 $finish;
    end

endmodule

sp.vcd
$date
	Wed Mar 04 11:26:44 2026
$end
$version
	Icarus Verilog
$end
$timescale
	1ps
$end
$scope module tb_stallable_pipeline $end
$var wire 1 ! validout $end
$var wire 100 " dataout [99:0] $end
$var parameter 32 # WIDTH $end
$var reg 1 $ clk $end
$var reg 100 % datain [99:0] $end
$var reg 1 & out_allow $end
$var reg 1 ' rst $end
$var reg 1 ( validin $end
$var integer 32 ) counter [31:0] $end
$scope module sp $end
$var wire 1 $ clk $end
$var wire 100 * datain [99:0] $end
$var wire 100 + dataout [99:0] $end
$var wire 1 & out_allow $end
$var wire 1 , pipe1_allowin $end
$var wire 1 - pipe1_ready_go $end
$var wire 1 . pipe1_to_pipe2_valid $end
$var wire 1 / pipe2_allowin $end
$var wire 1 0 pipe2_ready_go $end
$var wire 1 1 pipe2_to_pipe3_valid $end
$var wire 1 2 pipe3_allowin $end
$var wire 1 3 pipe3_ready_go $end
$var wire 1 4 pipe3_to_pipe4_valid $end
$var wire 1 5 pipe4_allowin $end
$var wire 1 6 pipe4_ready_go $end
$var wire 1 ' rst $end
$var wire 1 ( validin $end
$var wire 1 ! validout $end
$var parameter 32 7 WIDTH $end
$var reg 100 8 pipe1_data [99:0] $end
$var reg 1 9 pipe1_valid $end
$var reg 100 : pipe2_data [99:0] $end
$var reg 1 ; pipe2_valid $end
$var reg 100 < pipe3_data [99:0] $end
$var reg 1 = pipe3_valid $end
$var reg 100 > pipe4_data [99:0] $end
$var reg 1 ? pipe4_valid $end
$upscope $end
$upscope $end
$enddefinitions $end
$comment Show the parameter values. $end
$dumpall
b1100100 7
b1100100 #
$end
#0
$dumpvars
x?
bx >
x=
bx <
x;
bx :
x9
bx 8
16
15
x4
13
12
x1
10
1/
x.
1-
1,
bx +
b0 *
b0 )
0(
1'
1&
b0 %
0$
bx "
x!
$end
#5000
0.
01
04
0!
09
0;
0=
0?
1$
#10000
0$
1(
b1111111111111111111111111111111111111111111111111111111111111111111111111111111111111111111111111111 %
b1111111111111111111111111111111111111111111111111111111111111111111111111111111111111111111111111111 *
0'
#15000
1.
b1111111111111111111111111111111111111111111111111111111111111111111111111111111111111111111111111111 8
19
1$
#20000
0$
0(
#25000
0.
11
09
b1111111111111111111111111111111111111111111111111111111111111111111111111111111111111111111111111111 :
1;
1$
#30000
0$
#35000
14
01
b1111111111111111111111111111111111111111111111111111111111111111111111111111111111111111111111111111 <
1=
0;
1$
#40000
0$
#45000
04
1!
0=
b1111111111111111111111111111111111111111111111111111111111111111111111111111111111111111111111111111 "
b1111111111111111111111111111111111111111111111111111111111111111111111111111111111111111111111111111 +
b1111111111111111111111111111111111111111111111111111111111111111111111111111111111111111111111111111 >
1?
1$
#50000
0$
#55000
0!
0?
1$
#60000
0$
1(
b11001010111111101011101010111110 %
b11001010111111101011101010111110 *
#65000
1.
b11001010111111101011101010111110 8
19
1$
#70000
0$
0&
0(
#75000
11
0.
b11001010111111101011101010111110 :
1;
09
1$
#80000
0$
#85000
01
14
0;
b11001010111111101011101010111110 <
1=
1$
#90000
0$
#95000
05
1!
04
b11001010111111101011101010111110 "
b11001010111111101011101010111110 +
b11001010111111101011101010111110 >
1?
0=
1$
#100000
0$
#105000
1$
#110000
15
0$
1&
#115000
0!
0?
1$
#120000
0$
#125000
1$
#130000
0$
#135000
1$
#140000
0$
#145000
1$
#150000
0$
1'
#155000
1$
#160000
0$
#165000
1$
#170000
0$
0'
